streamlit_bmc/__init__.py
streamlit_bmc/frontend/public/.DS_Store
streamlit_bmc/frontend/public/index.html
streamlit_bmc/frontend/public/style.css
streamlit_bmc/frontend/public/build/bundle.css
streamlit_bmc/frontend/public/build/bundle.css.map
streamlit_bmc/frontend/public/build/bundle.js
streamlit_bmc/frontend/public/build/bundle.js.map
streamlit_bmc/frontend/public/img/.DS_Store
streamlit_bmc/frontend/public/img/bg-card-1.png
streamlit_bmc/frontend/public/img/bg-card-2.png
streamlit_bmc/frontend/public/img/bg-card-3.png
streamlit_bmc/frontend/public/img/bg-card-4.png
streamlit_bmc/frontend/public/img/bg-card-5.png
streamlit_bmc/frontend/public/img/bg-card-6.png
streamlit_bmc/frontend/public/img/bg-card-7.png
streamlit_bmc/frontend/public/img/bg-card-8.png
streamlit_bmc/frontend/public/img/bg-card-9.png
streamlit_bmc/frontend/public/img/bg.png
streamlit_bmc/frontend/public/img/icon-act.svg
streamlit_bmc/frontend/public/img/icon-cha.svg
streamlit_bmc/frontend/public/img/icon-cos.svg
streamlit_bmc/frontend/public/img/icon-par.svg
streamlit_bmc/frontend/public/img/icon-rel.svg
streamlit_bmc/frontend/public/img/icon-res.svg
streamlit_bmc/frontend/public/img/icon-rev.svg
streamlit_bmc/frontend/public/img/icon-seg.svg
streamlit_bmc/frontend/public/img/icon-val.svg
streamlit_bmc-0.0.4.dist-info/LICENSE
streamlit_bmc-0.0.4.dist-info/METADATA
streamlit_bmc-0.0.4.dist-info/WHEEL
streamlit_bmc-0.0.4.dist-info/top_level.txt
streamlit_bmc-0.0.4.dist-info/RECORD
