Metadata-Version: 2.1
Name: streamlit-bmc
Version: 0.0.4
Summary: A Streamlit Component for drawing Business Model Canvas
Home-page: https://github.com/teq-thuynguyen/streamlit-business_model_canvas
Author: Ember
Author-email: nguyencaonguyenthuy@gmail.com
License: UNKNOWN
Platform: UNKNOWN
Requires-Python: >=3.6
License-File: LICENSE
Requires-Dist: streamlit (>=0.63)
